Metadata-Version: 1.1
Name: megatemp
Version: 0.1.1
Summary: A utility for agm.
Home-page: https://github.com/Brian-Williams/actagm
Author: Brian Williams
Author-email: briancmwilliams@gmail.com
License: UNKNOWN
Keywords: automation
Platform: UNKNOWN
Classifier: Development Status :: 3 - Alpha
Classifier: Intended Audience :: Developers
Classifier: Programming Language :: Python :: 2
Classifier: Programming Language :: Python :: 2.7
Classifier: Programming Language :: Python :: 3
Classifier: Programming Language :: Python :: 3.4
Classifier: Programming Language :: Python :: 3.5
Classifier: Programming Language :: Python :: 3.6
